[
    {
        "docid": 15780,
        "tfidf": 0.022550380156565016,
        "fields": [
            "p"
        ],
        "Tokenfre": 2,
        "WordsInDocid": 394,
        "Positions": [
            293,
            299
        ]
    },
    {
        "docid": 15904,
        "tfidf": 0.004683670214406274,
        "fields": [
            "p"
        ],
        "Tokenfre": 258,
        "WordsInDocid": 244711,
        "Positions": [
            3740,
            3747,
            15817,
            22741,
            22750,
            28399,
            28408,
            28409,
            28417,
            28418,
            28427,
            28428,
            28437,
            28448,
            28457,
            30122,
            30132,
            30142,
            42151,
            42159,
            47222,
            47232,
            50719,
            50728,
            50729,
            50738,
            50739,
            50748,
            56318,
            56326,
            59694,
            59702,
            59711,
            59721,
            65799,
            65807,
            65808,
            65816,
            72224,
            72235,
            72245,
            75718,
            75726,
            81884,
            81892,
            81893,
            81901,
            81902,
            81910,
            81911,
            81919,
            81920,
            81928,
            81929,
            81937,
            81938,
            81946,
            81947,
            81955,
            81956,
            81964,
            81965,
            81973,
            83759,
            83769,
            83779,
            96148,
            119967,
            119979,
            130626,
            130633,
            130634,
            130641,
            130642,
            130649,
            140402,
            140412,
            140422,
            140432,
            140442,
            140452,
            140462,
            140472,
            140482,
            140492,
            140502,
            140512,
            140522,
            144522,
            144533,
            144534,
            144545,
            144555,
            144565,
            144566,
            144576,
            144577,
            144587,
            144588,
            144598,
            144599,
            144609,
            144610,
            144620,
            159984,
            159995,
            159996,
            160007,
            160008,
            160019,
            160020,
            160031,
            160032,
            160043,
            160044,
            160055,
            163435,
            163442,
            171572,
            174435,
            174443,
            174444,
            174452,
            174453,
            174461,
            174462,
            174470,
            184388,
            184395,
            187283,
            187293,
            187314,
            187322,
            187323,
            187331,
            187332,
            187340,
            187818,
            187826,
            187827,
            187835,
            188393,
            188400,
            188401,
            188408,
            188409,
            188416,
            188417,
            188424,
            188425,
            188432,
            188445,
            188452,
            188453,
            188460,
            188461,
            188468,
            188469,
            188476,
            188477,
            188484,
            188485,
            188492,
            188493,
            188500,
            188501,
            188508,
            188509,
            188516,
            188517,
            188524,
            188525,
            188532,
            188533,
            188540,
            188541,
            188548,
            188549,
            188556,
            188557,
            188564,
            188565,
            188572,
            204100,
            209231,
            209238,
            209239,
            209246,
            209247,
            209254,
            210136,
            210149,
            212974,
            212981,
            212984,
            212991,
            213061,
            213071,
            213072,
            213081,
            213082,
            213092,
            213112,
            213121,
            213200,
            213208,
            213210,
            213219,
            213220,
            213228,
            221169,
            221180,
            221181,
            221192,
            221193,
            221204,
            221978,
            221985,
            221986,
            221993,
            222506,
            222513,
            222516,
            222523,
            222526,
            222533,
            222623,
            222630,
            226551,
            226560,
            226568,
            226578,
            232258,
            232268,
            232269,
            232279,
            232280,
            232290,
            232818,
            232824,
            232825,
            232831,
            232832,
            232838,
            232839,
            232845,
            232846,
            232852,
            232853,
            232859,
            239305,
            239315,
            239325,
            239334,
            244306,
            244317,
            244318,
            244329
        ]
    },
    {
        "docid": 19319,
        "tfidf": 1.2317686601696966e-05,
        "fields": [
            "p"
        ],
        "Tokenfre": 1,
        "WordsInDocid": 385093,
        "Positions": [
            229283
        ]
    },
    {
        "docid": 21092,
        "tfidf": 0.03412557472307403,
        "fields": [
            "p"
        ],
        "Tokenfre": 1,
        "WordsInDocid": 139,
        "Positions": [
            90
        ]
    },
    {
        "docid": 35475,
        "tfidf": 0.005001047606028665,
        "fields": [
            "p"
        ],
        "Tokenfre": 258,
        "WordsInDocid": 244711,
        "Positions": [
            8320,
            8552,
            22360,
            22444,
            22454,
            22464,
            22498,
            22508,
            22518,
            22528,
            22538,
            22548,
            22558,
            22568,
            22639,
            22837,
            23173,
            23183,
            23193,
            23203,
            23213,
            23223,
            23233,
            23243,
            23253,
            23263,
            23273,
            23333,
            23343,
            43606,
            43613,
            45521,
            66061,
            66069,
            66071,
            66080,
            78521,
            82733,
            82744,
            90226,
            90697,
            116816,
            116823,
            116824,
            116831,
            116832,
            116839,
            116840,
            116847,
            116848,
            116856,
            116857,
            116864,
            116865,
            116872,
            116873,
            116881,
            116882,
            116890,
            116891,
            116899,
            116900,
            116909,
            116910,
            116918,
            116919,
            116927,
            116928,
            116936,
            116937,
            116945,
            116946,
            116954,
            116955,
            116963,
            116964,
            116972,
            116973,
            116981,
            116982,
            116992,
            117003,
            117004,
            117015,
            117016,
            117026,
            117027,
            117038,
            117039,
            117050,
            117051,
            117060,
            117061,
            117070,
            117071,
            117080,
            117081,
            117090,
            117091,
            117099,
            117100,
            117108,
            117109,
            117116,
            117117,
            117124,
            117125,
            117132,
            117133,
            117140,
            117141,
            117148,
            117149,
            117156,
            117157,
            117164,
            117165,
            117172,
            117173,
            117180,
            117181,
            117188,
            117189,
            117196,
            117197,
            117204,
            117205,
            117212,
            117213,
            117220,
            117221,
            117228,
            117229,
            117236,
            117237,
            117244,
            117245,
            117252,
            117253,
            117260,
            117261,
            117268,
            117269,
            117276,
            117277,
            117285,
            117286,
            117294,
            117295,
            117303,
            117304,
            117312,
            117313,
            117321,
            117322,
            117333,
            117334,
            117345,
            117346,
            117357,
            117358,
            117369,
            117370,
            117381,
            117382,
            117393,
            117394,
            117402,
            117403,
            117411,
            117412,
            117418,
            117419,
            117425,
            117426,
            117432,
            117433,
            117439,
            117440,
            117446,
            117447,
            117453,
            117454,
            117462,
            117463,
            117472,
            117473,
            117485,
            117486,
            117496,
            117497,
            117506,
            117507,
            117517,
            117518,
            117531,
            117532,
            117543,
            117544,
            117555,
            117556,
            117567,
            117568,
            117577,
            117578,
            117587,
            117588,
            117598,
            117599,
            117609,
            117610,
            117620,
            117621,
            117631,
            117632,
            117642,
            117643,
            117653,
            117654,
            117662,
            117663,
            117671,
            117672,
            117682,
            117683,
            117693,
            117694,
            117704,
            117705,
            117712,
            117713,
            117720,
            117721,
            117728,
            117729,
            117737,
            117738,
            117747,
            117748,
            117756,
            117757,
            137122,
            162790,
            162797,
            162800,
            162807,
            162810,
            162817,
            162820,
            162827,
            162830,
            162837,
            162840,
            162847,
            172468,
            203913,
            203920,
            216279
        ]
    },
    {
        "docid": 48337,
        "tfidf": 0.016189265824256963,
        "fields": [
            "p"
        ],
        "Tokenfre": 1,
        "WordsInDocid": 293,
        "Positions": [
            165
        ]
    }
]