[
    {
        "docid": 998,
        "tfidf": 0.002456475860438783,
        "fields": [
            "p"
        ],
        "Tokenfre": 1,
        "WordsInDocid": 1931,
        "Positions": [
            662
        ]
    },
    {
        "docid": 1320,
        "tfidf": 0.029833049600674778,
        "fields": [
            "p",
            "h2"
        ],
        "Tokenfre": 2,
        "WordsInDocid": 318,
        "Positions": [
            59,
            77
        ]
    },
    {
        "docid": 1791,
        "tfidf": 0.014777118026502459,
        "fields": [
            "p"
        ],
        "Tokenfre": 1,
        "WordsInDocid": 321,
        "Positions": [
            266
        ]
    },
    {
        "docid": 2495,
        "tfidf": 0.030631166241283238,
        "fields": [
            "p"
        ],
        "Tokenfre": 7,
        "WordsInDocid": 1084,
        "Positions": [
            338,
            371,
            386,
            475,
            501,
            538,
            603
        ]
    },
    {
        "docid": 2515,
        "tfidf": 0.003517359375172849,
        "fields": [
            "p"
        ],
        "Tokenfre": 1,
        "WordsInDocid": 1263,
        "Positions": [
            95,
            173,
            267,
            332,
            365,
            442,
            470,
            708
        ]
    },
    {
        "docid": 2519,
        "tfidf": 0.011814959816072628,
        "fields": [
            "p"
        ],
        "Tokenfre": 7,
        "WordsInDocid": 2632,
        "Positions": [
            790,
            1087,
            1389,
            1423,
            1512,
            1568,
            1694
        ]
    },
    {
        "docid": 3154,
        "tfidf": 0.004885123467051791,
        "fields": [
            "p"
        ],
        "Tokenfre": 1,
        "WordsInDocid": 971,
        "Positions": [
            125
        ]
    },
    {
        "docid": 3590,
        "tfidf": 0.006955212443559075,
        "fields": [
            "p"
        ],
        "Tokenfre": 1,
        "WordsInDocid": 682,
        "Positions": [
            449
        ]
    },
    {
        "docid": 6504,
        "tfidf": 0.002597909292890824,
        "fields": [
            "p"
        ],
        "Tokenfre": 1,
        "WordsInDocid": 1710,
        "Positions": [
            945
        ]
    },
    {
        "docid": 6684,
        "tfidf": 0.007807425115717589,
        "fields": [
            "p"
        ],
        "Tokenfre": 1,
        "WordsInDocid": 569,
        "Positions": [
            247
        ]
    },
    {
        "docid": 7110,
        "tfidf": 0.01447646455699071,
        "fields": [
            "p"
        ],
        "Tokenfre": 3,
        "WordsInDocid": 983,
        "Positions": [
            16,
            201,
            341
        ]
    },
    {
        "docid": 8460,
        "tfidf": 0.0037058241300838204,
        "fields": [
            "p"
        ],
        "Tokenfre": 1,
        "WordsInDocid": 1280,
        "Positions": [
            112,
            190,
            284,
            349,
            382,
            459,
            487,
            725
        ]
    },
    {
        "docid": 10245,
        "tfidf": 0.007541263730536232,
        "fields": [
            "p"
        ],
        "Tokenfre": 1,
        "WordsInDocid": 629,
        "Positions": [
            448
        ]
    },
    {
        "docid": 10862,
        "tfidf": 0.007840421300012048,
        "fields": [
            "p"
        ],
        "Tokenfre": 1,
        "WordsInDocid": 605,
        "Positions": [
            241
        ]
    },
    {
        "docid": 11012,
        "tfidf": 0.004594027808524621,
        "fields": [
            "p"
        ],
        "Tokenfre": 1,
        "WordsInDocid": 967,
        "Positions": [
            670
        ]
    },
    {
        "docid": 11183,
        "tfidf": 0.007947092827984451,
        "fields": [
            "p"
        ],
        "Tokenfre": 1,
        "WordsInDocid": 559,
        "Positions": [
            426
        ]
    },
    {
        "docid": 12198,
        "tfidf": 0.001391450538723171,
        "fields": [
            "p"
        ],
        "Tokenfre": 1,
        "WordsInDocid": 3409,
        "Positions": [
            3097
        ]
    },
    {
        "docid": 13893,
        "tfidf": 0.0032623486152044633,
        "fields": [
            "p"
        ],
        "Tokenfre": 1,
        "WordsInDocid": 1454,
        "Positions": [
            952
        ]
    },
    {
        "docid": 14882,
        "tfidf": 0.00011556717959574344,
        "fields": [
            "p"
        ],
        "Tokenfre": 1,
        "WordsInDocid": 41045,
        "Positions": [
            39939
        ]
    },
    {
        "docid": 15834,
        "tfidf": 0.001870494690881393,
        "fields": [
            "p"
        ],
        "Tokenfre": 1,
        "WordsInDocid": 2375,
        "Positions": [
            1110
        ]
    },
    {
        "docid": 15990,
        "tfidf": 0.015837521892489513,
        "fields": [
            "p"
        ],
        "Tokenfre": 2,
        "WordsInDocid": 561,
        "Positions": [
            55,
            314
        ]
    },
    {
        "docid": 16763,
        "tfidf": 0.02645049193219678,
        "fields": [
            "p"
        ],
        "Tokenfre": 3,
        "WordsInDocid": 538,
        "Positions": [
            108,
            391,
            413
        ]
    },
    {
        "docid": 17664,
        "tfidf": 0.0002585811927149772,
        "fields": [
            "p"
        ],
        "Tokenfre": 1,
        "WordsInDocid": 17180,
        "Positions": [
            95,
            173,
            267,
            332,
            365,
            442,
            470,
            708,
            8057,
            8064,
            8160,
            8197,
            11871,
            13244
        ]
    },
    {
        "docid": 17889,
        "tfidf": 0.004271562395041643,
        "fields": [
            "p"
        ],
        "Tokenfre": 1,
        "WordsInDocid": 1040,
        "Positions": [
            879
        ]
    },
    {
        "docid": 19319,
        "tfidf": 1.2317686601696966e-05,
        "fields": [
            "p"
        ],
        "Tokenfre": 1,
        "WordsInDocid": 385093,
        "Positions": [
            233811
        ]
    },
    {
        "docid": 20276,
        "tfidf": 0.002098873843587296,
        "fields": [
            "p"
        ],
        "Tokenfre": 1,
        "WordsInDocid": 2260,
        "Positions": [
            982
        ]
    },
    {
        "docid": 20843,
        "tfidf": 0.02919049160927563,
        "fields": [
            "p",
            "h2"
        ],
        "Tokenfre": 2,
        "WordsInDocid": 325,
        "Positions": [
            109,
            127
        ]
    },
    {
        "docid": 21244,
        "tfidf": 0.021859239108328522,
        "fields": [
            "p"
        ],
        "Tokenfre": 1,
        "WordsInDocid": 217,
        "Positions": [
            135
        ]
    },
    {
        "docid": 21665,
        "tfidf": 0.0044399838061424035,
        "fields": [
            "p"
        ],
        "Tokenfre": 4,
        "WordsInDocid": 3731,
        "Positions": [
            1082,
            1163,
            1192,
            1324
        ]
    },
    {
        "docid": 21844,
        "tfidf": 0.003054126028893309,
        "fields": [
            "p"
        ],
        "Tokenfre": 1,
        "WordsInDocid": 1356,
        "Positions": [
            1202
        ]
    },
    {
        "docid": 21866,
        "tfidf": 0.026979771304099853,
        "fields": [
            "p"
        ],
        "Tokenfre": 2,
        "WordsInDocid": 307,
        "Positions": [
            211,
            229
        ]
    },
    {
        "docid": 21924,
        "tfidf": 0.005619260373377648,
        "fields": [
            "p"
        ],
        "Tokenfre": 1,
        "WordsInDocid": 737,
        "Positions": [
            665
        ]
    },
    {
        "docid": 22839,
        "tfidf": 0.029554236053004918,
        "fields": [
            "p",
            "h2"
        ],
        "Tokenfre": 2,
        "WordsInDocid": 321,
        "Positions": [
            62,
            80
        ]
    },
    {
        "docid": 24175,
        "tfidf": 0.08500815208794425,
        "fields": [
            "p",
            "h1",
            "title",
            "head"
        ],
        "Tokenfre": 5,
        "WordsInDocid": 279,
        "Positions": [
            0,
            59,
            77,
            230
        ]
    },
    {
        "docid": 26876,
        "tfidf": 0.0027087956651483587,
        "fields": [
            "p"
        ],
        "Tokenfre": 1,
        "WordsInDocid": 1640,
        "Positions": [
            1356
        ]
    },
    {
        "docid": 26897,
        "tfidf": 9.183876810641091e-05,
        "fields": [
            "p"
        ],
        "Tokenfre": 1,
        "WordsInDocid": 48372,
        "Positions": [
            41441
        ]
    },
    {
        "docid": 27504,
        "tfidf": 0.001225698937081987,
        "fields": [
            "p"
        ],
        "Tokenfre": 1,
        "WordsInDocid": 3870,
        "Positions": [
            2843
        ]
    },
    {
        "docid": 28081,
        "tfidf": 0.04863968858587564,
        "fields": [
            "h3"
        ],
        "Tokenfre": 3,
        "WordsInDocid": 274,
        "Positions": []
    },
    {
        "docid": 28232,
        "tfidf": 0.0030553128547753153,
        "fields": [
            "p"
        ],
        "Tokenfre": 1,
        "WordsInDocid": 1454,
        "Positions": [
            1003
        ]
    },
    {
        "docid": 29287,
        "tfidf": 9.806199633067249e-05,
        "fields": [
            "p"
        ],
        "Tokenfre": 1,
        "WordsInDocid": 48372,
        "Positions": [
            10241
        ]
    },
    {
        "docid": 30742,
        "tfidf": 0.0009915248508585472,
        "fields": [
            "p"
        ],
        "Tokenfre": 1,
        "WordsInDocid": 4784,
        "Positions": [
            180,
            211
        ]
    },
    {
        "docid": 32433,
        "tfidf": 0.0031002973114426726,
        "fields": [
            "p"
        ],
        "Tokenfre": 1,
        "WordsInDocid": 1530,
        "Positions": [
            1266
        ]
    },
    {
        "docid": 33070,
        "tfidf": 0.002914162316794827,
        "fields": [
            "p"
        ],
        "Tokenfre": 1,
        "WordsInDocid": 1464,
        "Positions": [
            1078
        ]
    },
    {
        "docid": 33090,
        "tfidf": 0.006782724374861093,
        "fields": [
            "p"
        ],
        "Tokenfre": 1,
        "WordsInDocid": 629,
        "Positions": [
            448
        ]
    },
    {
        "docid": 33224,
        "tfidf": 0.006425201252692209,
        "fields": [
            "p"
        ],
        "Tokenfre": 1,
        "WordsInDocid": 664,
        "Positions": [
            548
        ]
    },
    {
        "docid": 34122,
        "tfidf": 0.014550475111985551,
        "fields": [
            "p"
        ],
        "Tokenfre": 1,
        "WordsInDocid": 326,
        "Positions": [
            74
        ]
    },
    {
        "docid": 35465,
        "tfidf": 0.0028923505405532256,
        "fields": [
            "p"
        ],
        "Tokenfre": 1,
        "WordsInDocid": 1640,
        "Positions": [
            1376
        ]
    },
    {
        "docid": 37093,
        "tfidf": 0.0110056957923603,
        "fields": [
            "p"
        ],
        "Tokenfre": 1,
        "WordsInDocid": 431,
        "Positions": [
            58
        ]
    },
    {
        "docid": 37895,
        "tfidf": 9.147536180710229e-05,
        "fields": [
            "p"
        ],
        "Tokenfre": 1,
        "WordsInDocid": 51855,
        "Positions": [
            51246
        ]
    },
    {
        "docid": 38253,
        "tfidf": 0.0012346316726984095,
        "fields": [
            "p"
        ],
        "Tokenfre": 1,
        "WordsInDocid": 3842,
        "Positions": [
            2509
        ]
    },
    {
        "docid": 38734,
        "tfidf": 0.006904592265658355,
        "fields": [
            "p"
        ],
        "Tokenfre": 2,
        "WordsInDocid": 1374,
        "Positions": [
            758,
            869,
            940
        ]
    },
    {
        "docid": 39320,
        "tfidf": 0.02645049193219678,
        "fields": [
            "p"
        ],
        "Tokenfre": 3,
        "WordsInDocid": 538,
        "Positions": [
            108,
            391,
            413
        ]
    },
    {
        "docid": 43261,
        "tfidf": 0.0110056957923603,
        "fields": [
            "p"
        ],
        "Tokenfre": 1,
        "WordsInDocid": 431,
        "Positions": [
            58
        ]
    },
    {
        "docid": 43642,
        "tfidf": 0.002903545680289744,
        "fields": [
            "p"
        ],
        "Tokenfre": 1,
        "WordsInDocid": 1530,
        "Positions": [
            1070
        ]
    },
    {
        "docid": 43869,
        "tfidf": 0.011078366311329945,
        "fields": [
            "p"
        ],
        "Tokenfre": 1,
        "WordsInDocid": 401,
        "Positions": [
            346
        ]
    },
    {
        "docid": 44207,
        "tfidf": 0.0027292605791181183,
        "fields": [
            "p"
        ],
        "Tokenfre": 1,
        "WordsInDocid": 1738,
        "Positions": [
            1469
        ]
    },
    {
        "docid": 46143,
        "tfidf": 0.025098445710979144,
        "fields": [
            "p"
        ],
        "Tokenfre": 2,
        "WordsInDocid": 354,
        "Positions": [
            290,
            295
        ]
    },
    {
        "docid": 46432,
        "tfidf": 0.0024671000874731445,
        "fields": [
            "p"
        ],
        "Tokenfre": 9,
        "WordsInDocid": 16206,
        "Positions": [
            4263,
            4286,
            5312,
            5317,
            6861,
            6866,
            7310,
            11462,
            12597
        ]
    },
    {
        "docid": 47147,
        "tfidf": 0.0013918588282004958,
        "fields": [
            "p"
        ],
        "Tokenfre": 1,
        "WordsInDocid": 3408,
        "Positions": [
            3019
        ]
    },
    {
        "docid": 49563,
        "tfidf": 0.007368451868372413,
        "fields": [
            "p"
        ],
        "Tokenfre": 1,
        "WordsInDocid": 579,
        "Positions": [
            285
        ]
    },
    {
        "docid": 49743,
        "tfidf": 0.009762777189445371,
        "fields": [
            "p"
        ],
        "Tokenfre": 1,
        "WordsInDocid": 437,
        "Positions": [
            382
        ]
    },
    {
        "docid": 49969,
        "tfidf": 0.004313785269754932,
        "fields": [
            "p"
        ],
        "Tokenfre": 1,
        "WordsInDocid": 989,
        "Positions": [
            582
        ]
    },
    {
        "docid": 52678,
        "tfidf": 0.0004471161171182288,
        "fields": [
            "p"
        ],
        "Tokenfre": 1,
        "WordsInDocid": 10609,
        "Positions": [
            8884
        ]
    },
    {
        "docid": 53563,
        "tfidf": 0.000755224132410295,
        "fields": [
            "p"
        ],
        "Tokenfre": 21,
        "WordsInDocid": 131898,
        "Positions": [
            6145,
            37757
        ]
    }
]