[
    {
        "docid": 26,
        "tfidf": 0.0030709312731658344,
        "fields": [
            "p"
        ],
        "Tokenfre": 1,
        "WordsInDocid": 780,
        "Positions": [
            677
        ]
    },
    {
        "docid": 29,
        "tfidf": 0.0018340937159795948,
        "fields": [
            "p"
        ],
        "Tokenfre": 1,
        "WordsInDocid": 1306,
        "Positions": [
            680
        ]
    },
    {
        "docid": 106,
        "tfidf": 0.03888516871865828,
        "fields": [
            "p",
            "p",
            "p",
            "p",
            "h1",
            "title",
            "head"
        ],
        "Tokenfre": 10,
        "WordsInDocid": 616,
        "Positions": [
            1,
            321,
            325,
            354,
            386,
            407,
            478,
            495,
            543,
            602
        ]
    },
    {
        "docid": 135,
        "tfidf": 0.0048984179817369135,
        "fields": [
            "p"
        ],
        "Tokenfre": 1,
        "WordsInDocid": 489,
        "Positions": [
            335
        ]
    },
    {
        "docid": 328,
        "tfidf": 0.0018340937159795948,
        "fields": [
            "p"
        ],
        "Tokenfre": 1,
        "WordsInDocid": 1306,
        "Positions": [
            680
        ]
    },
    {
        "docid": 438,
        "tfidf": 0.0272638776446918,
        "fields": [
            "p",
            "p",
            "p",
            "h2",
            "title",
            "head"
        ],
        "Tokenfre": 7,
        "WordsInDocid": 615,
        "Positions": [
            0,
            329,
            341,
            413,
            449,
            508
        ]
    },
    {
        "docid": 467,
        "tfidf": 0.0048984179817369135,
        "fields": [
            "p"
        ],
        "Tokenfre": 1,
        "WordsInDocid": 489,
        "Positions": [
            335
        ]
    },
    {
        "docid": 478,
        "tfidf": 0.00564491687290499,
        "fields": [
            "p",
            "p",
            "h2"
        ],
        "Tokenfre": 3,
        "WordsInDocid": 1273,
        "Positions": [
            679,
            691,
            763
        ]
    },
    {
        "docid": 616,
        "tfidf": 0.04091339496229952,
        "fields": [
            "p",
            "p",
            "p",
            "p",
            "h1",
            "title",
            "head"
        ],
        "Tokenfre": 10,
        "WordsInDocid": 616,
        "Positions": [
            1,
            321,
            325,
            354,
            386,
            407,
            478,
            495,
            543,
            602
        ]
    },
    {
        "docid": 625,
        "tfidf": 0.008466736157931637,
        "fields": [
            "p",
            "p"
        ],
        "Tokenfre": 3,
        "WordsInDocid": 893,
        "Positions": [
            369,
            374,
            516
        ]
    },
    {
        "docid": 638,
        "tfidf": 0.0036158753653911775,
        "fields": [
            "p"
        ],
        "Tokenfre": 2,
        "WordsInDocid": 1394,
        "Positions": [
            628,
            899,
            978,
            1026
        ]
    },
    {
        "docid": 640,
        "tfidf": 0.002086312193441764,
        "fields": [
            "p"
        ],
        "Tokenfre": 1,
        "WordsInDocid": 1208,
        "Positions": [
            671
        ]
    },
    {
        "docid": 700,
        "tfidf": 0.002086312193441764,
        "fields": [
            "p"
        ],
        "Tokenfre": 1,
        "WordsInDocid": 1208,
        "Positions": [
            671
        ]
    },
    {
        "docid": 933,
        "tfidf": 0.005902260256856325,
        "fields": [
            "p",
            "p",
            "h2"
        ],
        "Tokenfre": 3,
        "WordsInDocid": 1281,
        "Positions": [
            681,
            693,
            765
        ]
    },
    {
        "docid": 1005,
        "tfidf": 0.0035198254520043583,
        "fields": [
            "p"
        ],
        "Tokenfre": 2,
        "WordsInDocid": 1394,
        "Positions": [
            628,
            899,
            978,
            1026
        ]
    },
    {
        "docid": 1172,
        "tfidf": 0.001183120341457869,
        "fields": [
            "p",
            "p",
            "p",
            "p"
        ],
        "Tokenfre": 5,
        "WordsInDocid": 10368,
        "Positions": [
            3737,
            4130,
            5673,
            5884,
            5916
        ]
    },
    {
        "docid": 1241,
        "tfidf": 0.0018857174020346177,
        "fields": [
            "p"
        ],
        "Tokenfre": 1,
        "WordsInDocid": 1301,
        "Positions": [
            1050
        ]
    },
    {
        "docid": 1303,
        "tfidf": 0.0018857174020346177,
        "fields": [
            "p"
        ],
        "Tokenfre": 1,
        "WordsInDocid": 1301,
        "Positions": [
            1050
        ]
    },
    {
        "docid": 1340,
        "tfidf": 0.002495746022428319,
        "fields": [
            "p"
        ],
        "Tokenfre": 1,
        "WordsInDocid": 983,
        "Positions": [
            639,
            676
        ]
    },
    {
        "docid": 1364,
        "tfidf": 0.002495746022428319,
        "fields": [
            "p"
        ],
        "Tokenfre": 1,
        "WordsInDocid": 983,
        "Positions": [
            639,
            676
        ]
    },
    {
        "docid": 1468,
        "tfidf": 0.001183120341457869,
        "fields": [
            "p",
            "p",
            "p",
            "p"
        ],
        "Tokenfre": 5,
        "WordsInDocid": 10368,
        "Positions": [
            3737,
            4130,
            5673,
            5884,
            5916
        ]
    },
    {
        "docid": 1597,
        "tfidf": 0.0033326235586221484,
        "fields": [
            "p"
        ],
        "Tokenfre": 1,
        "WordsInDocid": 780,
        "Positions": [
            677
        ]
    },
    {
        "docid": 1673,
        "tfidf": 0.008732742583623545,
        "fields": [
            "p",
            "p"
        ],
        "Tokenfre": 3,
        "WordsInDocid": 893,
        "Positions": [
            369,
            374,
            516
        ]
    },
    {
        "docid": 1854,
        "tfidf": 0.0017135440841959627,
        "fields": [
            "p"
        ],
        "Tokenfre": 1,
        "WordsInDocid": 1517,
        "Positions": [
            803
        ]
    },
    {
        "docid": 1926,
        "tfidf": 0.0061259537526911455,
        "fields": [
            "p",
            "p",
            "h2"
        ],
        "Tokenfre": 3,
        "WordsInDocid": 1273,
        "Positions": [
            679,
            691,
            763
        ]
    },
    {
        "docid": 1945,
        "tfidf": 0.029587194520450295,
        "fields": [
            "p",
            "p",
            "p",
            "h2",
            "title",
            "head"
        ],
        "Tokenfre": 7,
        "WordsInDocid": 615,
        "Positions": [
            0,
            329,
            341,
            413,
            449,
            508
        ]
    }
]